{"v":"5.7.6","fr":24,"ip":12,"op":108,"w":1188,"h":1018,"nm":"罐子lottie","ddd":0,"assets":[{"id":"image_0","w":208,"h":206,"u":"images/","p":"img_0.png","e":0},{"id":"image_1","w":228,"h":228,"u":"images/","p":"img_1.png","e":0},{"id":"image_2","w":98,"h":98,"u":"images/","p":"img_2.png","e":0},{"id":"image_3","w":1174,"h":1010,"u":"images/","p":"img_3.png","e":0},{"id":"image_4","w":212,"h":214,"u":"images/","p":"img_4.png","e":0},{"id":"image_5","w":190,"h":190,"u":"images/","p":"img_5.png","e":0},{"id":"image_6","w":226,"h":344,"u":"images/","p":"img_6.png","e":0},{"id":"image_7","w":966,"h":492,"u":"images/","p":"img_7.png","e":0}],"layers":[{"ddd":0,"ind":1,"ty":2,"nm":"gaoguang.png","cl":"png","parent":5,"refId":"image_0","sr":1,"ks":{"o":{"a":1,"k":[{"i":{"x":[0.833],"y":[0.833]},"o":{"x":[0.167],"y":[0.167]},"t":4,"s":[0]},{"i":{"x":[0.833],"y":[0.833]},"o":{"x":[0.167],"y":[0.167]},"t":5,"s":[100]},{"t":84,"s":[100]}],"ix":11},"r":{"a":1,"k":[{"i":{"x":[0.833],"y":[0.833]},"o":{"x":[0.167],"y":[0.167]},"t":12,"s":[0]},{"i":{"x":[0.833],"y":[0.833]},"o":{"x":[0.167],"y":[0.167]},"t":60,"s":[20]},{"t":108,"s":[0]}],"ix":10},"p":{"a":0,"k":[372,110,0],"ix":2,"l":2},"a":{"a":0,"k":[104,103,0],"ix":1,"l":2},"s":{"a":1,"k":[{"i":{"x":[0.833,0.833,0.833],"y":[0.833,0.833,0.833]},"o":{"x":[0.167,0.167,0.167],"y":[0.167,0.167,0.167]},"t":12,"s":[100,100,100]},{"i":{"x":[0.833,0.833,0.833],"y":[0.833,0.833,0.833]},"o":{"x":[0.167,0.167,0.167],"y":[0.167,0.167,0.167]},"t":60,"s":[88,88,100]},{"t":108,"s":[100,100,100]}],"ix":6,"l":2}},"ao":0,"ip":0,"op":240,"st":0,"bm":0},{"ddd":0,"ind":2,"ty":2,"nm":"dianzhui2.png","cl":"png","parent":5,"refId":"image_1","sr":1,"ks":{"o":{"a":1,"k":[{"i":{"x":[0.833],"y":[0.833]},"o":{"x":[0.167],"y":[0.167]},"t":4,"s":[0]},{"i":{"x":[0.833],"y":[0.833]},"o":{"x":[0.167],"y":[0.167]},"t":5,"s":[100]},{"t":84,"s":[100]}],"ix":11},"r":{"a":0,"k":0,"ix":10},"p":{"a":1,"k":[{"i":{"x":0.833,"y":0.833},"o":{"x":0.167,"y":0.167},"t":12,"s":[1013,544,0],"to":[0,0,0],"ti":[0,0,0]},{"i":{"x":0.833,"y":0.833},"o":{"x":0.167,"y":0.167},"t":36,"s":[1013,518,0],"to":[0,0,0],"ti":[0,0,0]},{"i":{"x":0.833,"y":0.833},"o":{"x":0.167,"y":0.167},"t":60,"s":[1013,544,0],"to":[0,0,0],"ti":[0,0,0]},{"i":{"x":0.833,"y":0.833},"o":{"x":0.167,"y":0.167},"t":84,"s":[1013,518,0],"to":[0,0,0],"ti":[0,0,0]},{"t":108,"s":[1013,544,0]}],"ix":2,"l":2},"a":{"a":0,"k":[114,114,0],"ix":1,"l":2},"s":{"a":0,"k":[100,100,100],"ix":6,"l":2}},"ao":0,"ip":0,"op":240,"st":0,"bm":0},{"ddd":0,"ind":3,"ty":2,"nm":"xingxing.png","cl":"png","parent":5,"refId":"image_2","sr":1,"ks":{"o":{"a":1,"k":[{"i":{"x":[0.833],"y":[0.833]},"o":{"x":[0.167],"y":[0.167]},"t":4,"s":[0]},{"i":{"x":[0.833],"y":[0.833]},"o":{"x":[0.167],"y":[0.167]},"t":5,"s":[100]},{"t":84,"s":[100]}],"ix":11},"r":{"a":1,"k":[{"i":{"x":[0.833],"y":[0.833]},"o":{"x":[0.167],"y":[0.167]},"t":12,"s":[0]},{"i":{"x":[0.833],"y":[0.833]},"o":{"x":[0.167],"y":[0.167]},"t":36,"s":[-9]},{"i":{"x":[0.833],"y":[0.833]},"o":{"x":[0.167],"y":[0.167]},"t":60,"s":[0]},{"i":{"x":[0.833],"y":[0.833]},"o":{"x":[0.167],"y":[0.167]},"t":84,"s":[-9]},{"t":108,"s":[0]}],"ix":10},"p":{"a":1,"k":[{"i":{"x":0.833,"y":0.833},"o":{"x":0.167,"y":0.167},"t":12,"s":[199,423,0],"to":[0,0,0],"ti":[0,0,0]},{"i":{"x":0.833,"y":0.833},"o":{"x":0.167,"y":0.167},"t":36,"s":[209,417,0],"to":[0,0,0],"ti":[0,0,0]},{"i":{"x":0.833,"y":0.833},"o":{"x":0.167,"y":0.167},"t":60,"s":[199,423,0],"to":[0,0,0],"ti":[0,0,0]},{"i":{"x":0.833,"y":0.833},"o":{"x":0.167,"y":0.167},"t":84,"s":[209,417,0],"to":[0,0,0],"ti":[0,0,0]},{"t":108,"s":[199,423,0]}],"ix":2,"l":2},"a":{"a":0,"k":[49,49,0],"ix":1,"l":2},"s":{"a":0,"k":[100,100,100],"ix":6,"l":2}},"ao":0,"ip":0,"op":240,"st":0,"bm":0},{"ddd":0,"ind":4,"ty":2,"nm":"罐子Lottie.png","cl":"png","refId":"image_3","sr":1,"ks":{"o":{"a":0,"k":100,"ix":11},"r":{"a":0,"k":0,"ix":10},"p":{"a":0,"k":[596,507,0],"ix":2,"l":2},"a":{"a":0,"k":[587,505,0],"ix":1,"l":2},"s":{"a":0,"k":[100,100,100],"ix":6,"l":2}},"ao":0,"ip":0,"op":254,"st":0,"bm":0},{"ddd":0,"ind":5,"ty":3,"nm":"罐子.png","cl":"png","sr":1,"ks":{"o":{"a":1,"k":[{"i":{"x":[0.833],"y":[0.833]},"o":{"x":[0.167],"y":[0.167]},"t":4,"s":[0]},{"i":{"x":[0.833],"y":[0.833]},"o":{"x":[0.167],"y":[0.167]},"t":5,"s":[100]},{"t":84,"s":[100]}],"ix":11},"r":{"a":0,"k":0,"ix":10},"p":{"a":0,"k":[596,507,0],"ix":2,"l":2},"a":{"a":0,"k":[587,505,0],"ix":1,"l":2},"s":{"a":1,"k":[{"i":{"x":[0.833,0.833,0.833],"y":[0.833,0.833,0.833]},"o":{"x":[0.167,0.167,0.167],"y":[0.167,0.167,0.167]},"t":4,"s":[60,60,100]},{"i":{"x":[0.833,0.833,0.833],"y":[0.833,0.833,0.833]},"o":{"x":[0.167,0.167,0.167],"y":[0.167,0.167,0.167]},"t":8,"s":[110,110,100]},{"i":{"x":[0.833,0.833,0.833],"y":[0.833,0.833,0.833]},"o":{"x":[0.167,0.167,0.167],"y":[0.167,0.167,0.167]},"t":10,"s":[94,94,100]},{"i":{"x":[0.833,0.833,0.833],"y":[0.833,0.833,0.833]},"o":{"x":[0.167,0.167,0.167],"y":[0.167,0.167,0.167]},"t":12,"s":[100,100,100]},{"t":84,"s":[100,100,100]}],"ix":6,"l":2}},"ao":0,"ip":0,"op":254,"st":0,"bm":0},{"ddd":0,"ind":6,"ty":2,"nm":"dianzhui3.png","cl":"png","parent":5,"refId":"image_4","sr":1,"ks":{"o":{"a":1,"k":[{"i":{"x":[0.833],"y":[0.833]},"o":{"x":[0.167],"y":[0.167]},"t":11,"s":[0]},{"i":{"x":[0.833],"y":[0.833]},"o":{"x":[0.167],"y":[0.167]},"t":12,"s":[100]},{"t":84,"s":[100]}],"ix":11},"r":{"a":0,"k":0,"ix":10},"p":{"a":1,"k":[{"i":{"x":0.833,"y":0.833},"o":{"x":0.167,"y":0.167},"t":12,"s":[1060,284,0],"to":[0,0,0],"ti":[0,0,0]},{"i":{"x":0.833,"y":0.833},"o":{"x":0.167,"y":0.167},"t":36,"s":[1080,301,0],"to":[0,0,0],"ti":[0,0,0]},{"i":{"x":0.833,"y":0.833},"o":{"x":0.167,"y":0.167},"t":60,"s":[1060,284,0],"to":[0,0,0],"ti":[0,0,0]},{"i":{"x":0.833,"y":0.833},"o":{"x":0.167,"y":0.167},"t":84,"s":[1080,301,0],"to":[0,0,0],"ti":[0,0,0]},{"t":108,"s":[1060,284,0]}],"ix":2,"l":2},"a":{"a":0,"k":[106,107,0],"ix":1,"l":2},"s":{"a":0,"k":[100,100,100],"ix":6,"l":2}},"ao":0,"ip":0,"op":240,"st":0,"bm":0},{"ddd":0,"ind":7,"ty":2,"nm":"dianzhui4.png","cl":"png","parent":5,"refId":"image_5","sr":1,"ks":{"o":{"a":1,"k":[{"i":{"x":[0.833],"y":[0.833]},"o":{"x":[0.167],"y":[0.167]},"t":11,"s":[0]},{"i":{"x":[0.833],"y":[0.833]},"o":{"x":[0.167],"y":[0.167]},"t":12,"s":[100]},{"t":84,"s":[100]}],"ix":11},"r":{"a":0,"k":0,"ix":10},"p":{"a":1,"k":[{"i":{"x":0.833,"y":0.833},"o":{"x":0.167,"y":0.167},"t":12,"s":[131,320,0],"to":[0,0,0],"ti":[0,0,0]},{"i":{"x":0.833,"y":0.833},"o":{"x":0.167,"y":0.167},"t":36,"s":[144,342,0],"to":[0,0,0],"ti":[0,0,0]},{"i":{"x":0.833,"y":0.833},"o":{"x":0.167,"y":0.167},"t":60,"s":[131,320,0],"to":[0,0,0],"ti":[0,0,0]},{"i":{"x":0.833,"y":0.833},"o":{"x":0.167,"y":0.167},"t":84,"s":[144,342,0],"to":[0,0,0],"ti":[0,0,0]},{"t":108,"s":[131,320,0]}],"ix":2,"l":2},"a":{"a":0,"k":[95,95,0],"ix":1,"l":2},"s":{"a":0,"k":[100,100,100],"ix":6,"l":2}},"ao":0,"ip":0,"op":240,"st":0,"bm":0},{"ddd":0,"ind":8,"ty":2,"nm":"dianzhui5.png","cl":"png","parent":5,"refId":"image_6","sr":1,"ks":{"o":{"a":1,"k":[{"i":{"x":[0.833],"y":[0.833]},"o":{"x":[0.167],"y":[0.167]},"t":4,"s":[0]},{"i":{"x":[0.833],"y":[0.833]},"o":{"x":[0.167],"y":[0.167]},"t":5,"s":[100]},{"t":84,"s":[100]}],"ix":11},"r":{"a":1,"k":[{"i":{"x":[0.833],"y":[0.833]},"o":{"x":[0.167],"y":[0.167]},"t":12,"s":[-6]},{"i":{"x":[0.833],"y":[0.833]},"o":{"x":[0.167],"y":[0.167]},"t":36,"s":[0]},{"i":{"x":[0.833],"y":[0.833]},"o":{"x":[0.167],"y":[0.167]},"t":60,"s":[-6]},{"i":{"x":[0.833],"y":[0.833]},"o":{"x":[0.167],"y":[0.167]},"t":84,"s":[0]},{"t":108,"s":[-6]}],"ix":10},"p":{"a":0,"k":[259,697,0],"ix":2,"l":2},"a":{"a":0,"k":[179,211,0],"ix":1,"l":2},"s":{"a":0,"k":[100,100,100],"ix":6,"l":2}},"ao":0,"ip":0,"op":240,"st":0,"bm":0},{"ddd":0,"ind":9,"ty":2,"nm":"dianzhui.png","cl":"png","parent":5,"refId":"image_7","sr":1,"ks":{"o":{"a":1,"k":[{"i":{"x":[0.833],"y":[0.833]},"o":{"x":[0.167],"y":[0.167]},"t":11,"s":[0]},{"i":{"x":[0.833],"y":[0.833]},"o":{"x":[0.167],"y":[0.167]},"t":12,"s":[100]},{"t":108,"s":[100]}],"ix":11},"r":{"a":1,"k":[{"i":{"x":[0.833],"y":[0.833]},"o":{"x":[0.167],"y":[0.167]},"t":12,"s":[0]},{"i":{"x":[0.833],"y":[0.833]},"o":{"x":[0.167],"y":[0.167]},"t":60,"s":[-6]},{"t":108,"s":[0]}],"ix":10},"p":{"a":0,"k":[585,476,0],"ix":2,"l":2},"a":{"a":0,"k":[531,306,0],"ix":1,"l":2},"s":{"a":0,"k":[100,100,100],"ix":6,"l":2}},"ao":0,"ip":0,"op":240,"st":0,"bm":0}],"markers":[]}